attrsmallow/__init__.py
attrsmallow/__init__.pyc
attrsmallow/model_schema.py
attrsmallow/model_schema.pyc
attrsmallow/__pycache__/__init__.cpython-34.pyc
attrsmallow/__pycache__/__init__.cpython-35.pyc
attrsmallow/__pycache__/__init__.cpython-36.pyc
attrsmallow/__pycache__/model_schema.cpython-34.pyc
attrsmallow/__pycache__/model_schema.cpython-35.pyc
attrsmallow/__pycache__/model_schema.cpython-36.pyc
attrsmallow-0.0.1.dist-info/DESCRIPTION.rst
attrsmallow-0.0.1.dist-info/METADATA
attrsmallow-0.0.1.dist-info/RECORD
attrsmallow-0.0.1.dist-info/WHEEL
attrsmallow-0.0.1.dist-info/metadata.json
attrsmallow-0.0.1.dist-info/top_level.txt
